odoo/addons/project_list/README.rst
odoo/addons/project_list/__init__.py
odoo/addons/project_list/__manifest__.py
odoo/addons/project_list/i18n/de.po
odoo/addons/project_list/i18n/es_AR.po
odoo/addons/project_list/i18n/it.po
odoo/addons/project_list/i18n/project_list.pot
odoo/addons/project_list/i18n/sv.po
odoo/addons/project_list/readme/CONTRIBUTORS.rst
odoo/addons/project_list/readme/DESCRIPTION.rst
odoo/addons/project_list/static/description/icon.png
odoo/addons/project_list/static/description/index.html
odoo/addons/project_list/views/project_project.xml
odoo14_addon_project_list-14.0.1.0.1.dev7.dist-info/METADATA
odoo14_addon_project_list-14.0.1.0.1.dev7.dist-info/WHEEL
odoo14_addon_project_list-14.0.1.0.1.dev7.dist-info/top_level.txt
odoo14_addon_project_list-14.0.1.0.1.dev7.dist-info/RECORD
